bci4als/__init__.py
bci4als/_version.py
bci4als/eeg.py
bci4als/ml_model.py
bci4als/mouse.py
bci4als/dashboard/__init__.py
bci4als/experiments/__init__.py
bci4als/experiments/experiment.py
bci4als/experiments/feedback.py
bci4als/experiments/offline.py
bci4als/experiments/online.py
bci4als-0.36.1.dist-info/LICENSE
bci4als-0.36.1.dist-info/METADATA
bci4als-0.36.1.dist-info/WHEEL
bci4als-0.36.1.dist-info/top_level.txt
bci4als-0.36.1.dist-info/RECORD
