Metadata-Version: 2.1
Name: bci4als
Version: 0.36.1
Summary: A complete EEG Motor Imagery Classification pipeline
Home-page: https://github.com/evyatarluv/BCI-4-ALS
Author: Noam Siegel & Evyatar Luvaton
Author-email: noamsi@post.bgu.ac.il
License: MIT
Platform: UNKNOWN
Classifier: Development Status :: 2 - Pre-Alpha
Classifier: Intended Audience :: Developers
Classifier: License :: OSI Approved :: MIT License
Classifier: Natural Language :: English
Classifier: Programming Language :: Python :: 3
Classifier: Programming Language :: Python :: 3.5
Classifier: Programming Language :: Python :: 3.6
Classifier: Programming Language :: Python :: 3.7
Classifier: Programming Language :: Python :: 3.8
Requires-Python: >=3.6.0
License-File: LICENSE
Requires-Dist: numpy
Requires-Dist: pandas
Requires-Dist: sklearn
Requires-Dist: mne
Requires-Dist: mne-features
Requires-Dist: psychopy
